msci.sdk-1.28.1-py3.12-nspkg.pth
msci/sdk/__init__.py
msci/sdk/_version.py
msci/sdk/settings.py
msci/sdk/calc/__init__.py
msci/sdk/calc/portfolio/__init__.py
msci/sdk/calc/portfolio/mos/__init__.py
msci/sdk/calc/portfolio/mos/v1_4/__init__.py
msci/sdk/calc/portfolio/mos/v1_4/batch_jobs.py
msci/sdk/calc/portfolio/mos/v1_4/bulk_result.py
msci/sdk/calc/portfolio/mos/v1_4/client_portfolio.py
msci/sdk/calc/portfolio/mos/v1_4/constraints.py
msci/sdk/calc/portfolio/mos/v1_4/enums.py
msci/sdk/calc/portfolio/mos/v1_4/full_optimizer_node.py
msci/sdk/calc/portfolio/mos/v1_4/initial_portfolio.py
msci/sdk/calc/portfolio/mos/v1_4/job.py
msci/sdk/calc/portfolio/mos/v1_4/metrics.py
msci/sdk/calc/portfolio/mos/v1_4/mos_config.py
msci/sdk/calc/portfolio/mos/v1_4/mos_session.py
msci/sdk/calc/portfolio/mos/v1_4/mso_templates.py
msci/sdk/calc/portfolio/mos/v1_4/optimizer_result.py
msci/sdk/calc/portfolio/mos/v1_4/partial_optimiser.py
msci/sdk/calc/portfolio/mos/v1_4/profile.py
msci/sdk/calc/portfolio/mos/v1_4/results.py
msci/sdk/calc/portfolio/mos/v1_4/rule_based_nodes.py
msci/sdk/calc/portfolio/mos/v1_4/templates.py
msci/sdk/calc/portfolio/mos/v1_4/user_datapoints.py
msci/sdk/calc/portfolio/omps/__init__.py
msci/sdk/calc/portfolio/omps/omps_service.py
msci/sdk/calc/portfolio/resources/bid_to_mds_uid.csv
msci/sdk/calc/portfolio/resources/taxlots.csv
msci/sdk/calc/portfolio/resources/taxlots.json
msci/sdk/calc/portfolio/resources/taxlots_trading_rule.json
msci/sdk/calc/portfolio/utils/__init__.py
msci/sdk/calc/portfolio/utils/constants.py
msci/sdk/calc/portfolio/utils/dataclass_validations.py
msci/sdk/calc/portfolio/utils/job_utility.py
msci/sdk/calc/portfolio/utils/metric.py
msci/sdk/calc/portfolio/utils/request_utility.py
msci/sdk/calc/portfolio/utils/utility.py
msci/sdk/calc/portfolio/utils/validations.py
msci/sdk/calc/security/__init__.py
msci/sdk/data/__init__.py
msci/sdk/data/connection.py
msci/sdk/data/data_mapper.py
msci/sdk/data/analytics/__init__.py
msci_sdk-1.28.1.dist-info/METADATA
msci_sdk-1.28.1.dist-info/WHEEL
msci_sdk-1.28.1.dist-info/namespace_packages.txt
msci_sdk-1.28.1.dist-info/top_level.txt
msci_sdk-1.28.1.dist-info/RECORD
