Metadata-Version: 2.4
Name: msci.sdk
Version: 1.28.1
Summary: Provides easy interface for users to integrate MSCI APIs, content and data into their own choice of platform.
Home-page: https://developer.msci.com/code-libraries/msci-python-sdk
Author: MSCI
Author-email: msci_sdk@msci.com
License: MSCI
Project-URL: Documentation, https://developer.msci.com/code-libraries/msci-python-sdk
Requires-Python: >=3.8
Requires-Dist: sqlalchemy
Requires-Dist: requests
Requires-Dist: PyYAML
Requires-Dist: pandas
Requires-Dist: cachetools
Requires-Dist: cryptography
Provides-Extra: doc-build
Requires-Dist: jinja2==3.1.2; extra == "doc-build"
Requires-Dist: pydata-sphinx-theme==0.13.3; extra == "doc-build"
Requires-Dist: sphinx; extra == "doc-build"
Requires-Dist: msci.sphinx_tools; extra == "doc-build"
Dynamic: author
Dynamic: author-email
Dynamic: description
Dynamic: description-content-type
Dynamic: home-page
Dynamic: license
Dynamic: project-url
Dynamic: provides-extra
Dynamic: requires-dist
Dynamic: requires-python
Dynamic: summary
